localimport/__init__.py
localimport/py.typed
localimport-1.7.5.dist-info/LICENSE
localimport-1.7.5.dist-info/WHEEL
localimport-1.7.5.dist-info/METADATA
localimport-1.7.5.dist-info/RECORD
